[
  {
    "Name": "Shield",
    "ShortName": "Shield",
    "Color": "{default}",
    "HammerID": "3792",
    "GlowColor": [250,2,246,255],
    "FilterID": 0,
    "FilterValue": "",
    "BlockPickup": false,
    "AllowTransfer": true,
    "ForceDrop": true,
    "Chat": true,
    "Hud": true,
    "TriggerID": "0",
    "UsePriority": true,
    "AbilityList": [
      {
        "Name": "Item_Shield_Button",
        "ButtonID": "2690",
        "ButtonClass": "func_button",
        "Filter": "player_shield",
        "Chat_Uses": true,
        "Mode": 2,
        "MaxUses": 0,
        "CoolDown": 80
      }
    ]
  },
  {
    "Name": "Push",
    "ShortName": "Push",
    "Color": "{default}",
    "HammerID": "4310",
    "GlowColor": [250,2,246,255],
    "FilterID": 0,
    "FilterValue": "",
    "BlockPickup": false,
    "AllowTransfer": true,
    "ForceDrop": true,
    "Chat": true,
    "Hud": true,
    "TriggerID": "0",
    "UsePriority": true,
    "AbilityList": [
      {
        "Name": "Item_Push_Button",
        "ButtonID": "2511",
        "ButtonClass": "func_button",
        "Filter": "player_push",
        "Chat_Uses": true,
        "Mode": 2,
        "MaxUses": 0,
        "CoolDown": 50
      }
    ]
  },
  {
    "Name": "Heal",
    "ShortName": "Heal",
    "Color": "{default}",
    "HammerID": "3169",
    "GlowColor": [250,2,246,255],
    "FilterID": 0,
    "FilterValue": "",
    "BlockPickup": false,
    "AllowTransfer": true,
    "ForceDrop": true,
    "Chat": true,
    "Hud": true,
    "TriggerID": "0",
    "UsePriority": true,
    "AbilityList": [
      {
        "Name": "Item_Heal_Button",
        "ButtonID": "2857",
        "ButtonClass": "func_button",
        "Filter": "player_heal",
        "Chat_Uses": true,
        "Mode": 2,
        "MaxUses": 0,
        "CoolDown": 80
      }
    ]
  },
  {
    "Name": "Gravity",
    "ShortName": "Gravity",
    "Color": "{default}",
    "HammerID": "2845",
    "GlowColor": [250,2,246,255],
    "FilterID": 0,
    "FilterValue": "",
    "BlockPickup": false,
    "AllowTransfer": true,
    "ForceDrop": true,
    "Chat": true,
    "Hud": true,
    "TriggerID": "0",
    "UsePriority": true,
    "AbilityList": [
      {
        "Name": "Item_Gravity_Button",
        "ButtonID": "2848",
        "ButtonClass": "func_button",
        "Filter": "player_gravity",
        "Chat_Uses": true,
        "Mode": 2,
        "MaxUses": 0,
        "CoolDown": 60
      }
    ]
  },
  {
    "Name": "ZM Reverse",
    "ShortName": "ZM Reverse",
    "Color": "{default}",
    "HammerID": "2029",
    "GlowColor": [250,2,246,255],
    "FilterID": 0,
    "FilterValue": "",
    "BlockPickup": false,
    "AllowTransfer": true,
    "ForceDrop": true,
    "Chat": true,
    "Hud": true,
    "TriggerID": "0",
    "UsePriority": true,
    "AbilityList": [
      {
        "Name": "Item_ZReverse_Button",
        "ButtonID": "4353",
        "ButtonClass": "func_button",
        "Filter": "player_zcube",
        "Chat_Uses": true,
        "Mode": 2,
        "MaxUses": 0,
        "CoolDown": 80
      }
    ]
  },
  {
    "Name": "ZM Heal",
    "ShortName": "ZM Heal",
    "Color": "{default}",
    "HammerID": "4570",
    "GlowColor": [250,2,246,255],
    "FilterID": 0,
    "FilterValue": "",
    "BlockPickup": false,
    "AllowTransfer": true,
    "ForceDrop": true,
    "Chat": true,
    "Hud": true,
    "TriggerID": "0",
    "UsePriority": true,
    "AbilityList": [
      {
        "Name": "Item_ZHeal_Button",
        "ButtonID": "4356",
        "ButtonClass": "func_button",
        "Filter": "player_zheal",
        "Chat_Uses": true,
        "Mode": 2,
        "MaxUses": 0,
        "CoolDown": 50
      }
    ]
  },
  {
    "Name": "ZM Water",
    "ShortName": "ZM Water",
    "Color": "{default}",
    "HammerID": "2958",
    "GlowColor": [250,2,246,255],
    "FilterID": 0,
    "FilterValue": "",
    "BlockPickup": false,
    "AllowTransfer": true,
    "ForceDrop": true,
    "Chat": true,
    "Hud": true,
    "TriggerID": "0",
    "UsePriority": true,
    "AbilityList": [
      {
        "Name": "Item_ZWater_Button",
        "ButtonID": "2728",
        "ButtonClass": "func_button",
        "Filter": "player_zwater",
        "Chat_Uses": true,
        "Mode": 2,
        "MaxUses": 0,
        "CoolDown": 70
      }
    ]
  },
  {
    "Name": "ZM Cube",
    "ShortName": "ZM Cube",
    "Color": "{default}",
    "HammerID": "2941",
    "GlowColor": [250,2,246,255],
    "FilterID": 0,
    "FilterValue": "",
    "BlockPickup": false,
    "AllowTransfer": true,
    "ForceDrop": true,
    "Chat": true,
    "Hud": true,
    "TriggerID": "0",
    "UsePriority": true,
    "AbilityList": [
      {
        "Name": "Item_ZCube_Button",
        "ButtonID": "3697",
        "ButtonClass": "func_button",
        "Filter": "player_zcube",
        "Chat_Uses": true,
        "Mode": 2,
        "MaxUses": 0,
        "CoolDown": 60
      }
    ]
  }
]